[
  {
    "level": "chapter",
    "number": "1",
    "title": "The Benefits of Bodhicitta from Engaging in the Bodhisattva's Conduct",
    "verses_span": "1-36",
    "verse_text_excerpt": "བདེ་གཤེགས་ཆོས་ཀྱི་སྐུ་མངའ་སྲས་བཅས་དང་། །ཕྱག་འོས་ཀུན་ལའང་གུས་པར་ཕྱག་འཚལ་ཏེ། །\n\nབདེ་གཤེགས་སྲས་ཀྱི་སྡོམ་ལ་འཇུག་པ་ནི། །ལུང་བཞིན་མདོར་བསྡུས་ནས་ནི་བརྗོད་པར་བྱ། །\nསྔོན་ཆད་མ་བྱུང་བ་ཡང་འདིར་བརྗོད་མེད། །སྡེབ་སྦྱོར་མཁས་པའང་བདག་ལ་ཡོད་མིན་ཏེ། །དེ་ཕྱིར་གཞན་དོན་བསམ་པ་བདག་ལ་མེད། །རང་གི་ཡིད་ལ་བསྒོམ་ཕྱིར་ངས་འདི་བརྩམས། །\nདགེ་བ་བསྒོམ་ཕྱིར་བདག་གི་དད་པའི་ཤུགས། །འདི་དག་གིས་ཀྱང་རེ་ཞིག་འཕེལ་འགྱུར་ལ། །བདག་དང་སྐལ་བ་མཉམ་པ་གཞན་གྱིས་ཀྱང་། །ཅི་སྟེ་འདི་དག་མཐོང་ན་དོན་ཡོད་འགྱུར། །\n\nདལ་འབྱོར་འདི་ནི་རྙེད་པར་ཤིན་ཏུ་དཀའ། །སྐྱེས་བུའི་དོན་སྒྲུབ་ཐོབ་པར་གྱུར་པ་ལ། །གལ་ཏེ་འདི་ལ་ཕན་པ་མ་བསྒྲུབས་ན། །ཕྱིས་འདི་ཡང་དག་འབྱོར་པར་ག་ལ་འགྱུར། །\n\nཇི་ལྟར་མཚན་མོ་མུན་ནག་སྤྲིན་རུམ་ན། །གློག་འགྱུ་སྐད་ཅིག་རབ་སྣང་སྟོན་པ་ལྟར། །དེ་བཞིན་སངས་རྒྱས་མཐུ་ཡིས་བརྒྱ་ལམ་ན། །འཇིག་རྟེན་བསོད་ནམས་བློ་གྲོས་ཐང་འགའ་འབྱུང་། །\n\nདེ་ལྟས་དགེ་བ་ཉམ་ཆུང་ཉིད་ལ་རྟག །སྡིག་པ་སྟོབས་ཆེན་ཤིན་ཏུ་མི་བཟད་པ། །དེ་ནི་རྫོགས་པའི་བྱང་ཆུབ་སེམས་མིན་པ། །དགེ་གཞན་གང་གིས་ཟིལ་གྱིས་གནོན་པར་འགྱུར། །\nབསྐལ་པ་དུ་མར་རབ་དགོངས་མཛད་པ་ཡི། །ཐུབ་དབང་རྣམས་ཀྱིས་འདི་ཉིད་ཕན་པར་གཟིགས། །འདིས་ནི་ཚད་མེད་སྐྱེ་བོའི་ཚོགས་རྣམས་ཀྱིས། །བདེ་མཆོག་བདེ་བླག་ཉིད་དུ་ཐོབ་པར་བྱེད། །\nསྲིད་པའི་སྡུག་བསྔལ་བརྒྱ་ཕྲག་གཞོམ་འདོད་ཅིང་། །སེམས་ཅན་མི་བདེ་བསལ་བར་འདོད་པ་དང་། །བདེ་མང་བརྒྱ་ཕྲག་སྤྱོད་པར་འདོད་པས་ཀྱང་། །བྱང་ཆུབ་སེམས་ཉིད་རྟག་ཏུ་གཏང་མི་བྱ། །\n\nབྱང་ཆུབ་སེམས་སྐྱེས་གྱུར་ན་སྐད་ཅིག་གིས། །འཁོར་བའི་བཙོན་རར་བསྡམས་པའི་ཉམ་ཐག་རྣམས། །བདེ་གཤེགས་རྣམས་ཀྱི་སྲས་ཞེས་བརྗོད་བྱ་ཞིང་། །འཇིག་རྟེན་ལྷ་མིར་བཅས་པས་ཕྱག་བྱར་འགྱུར། །\n\nགསེར་འགྱུར་རྩི་ཡི་རྣམ་པ་མཆོག་ལྟ་བུ། །མི་གཙང་ལུས་འདི་བླངས་ནས་རྒྱལ་བའི་སྐུ། །རིན་ཆེན་རིང་ཐང་མེད་པར་བསྒྱུར་བས་ན། །བྱང་ཆུབ་སེམས་ཞེས་བྱ་བ་རབ་བརྟན་ཟུང་། །\n\nའགྲོ་བའི་དེད་དཔོན་གཅིག་པུ་ཚད་མེད་བློས། །ལེགས་པར་ཡོངས་སུ་བརྟགས་ན་རིན་ཆེ་བས། །འགྲོ་བའི་གནས་དང་བྲལ་བར་འདོད་པ་རྣམས། །རིན་ཆེན་བྱང་ཆུབ་སེམས་ལེགས་བརྟན་པར་ཟུང་། །\n\nདགེ་བ་གཞན་ཀུན་ཆུ་ཤིང་བཞིན་དུ་ནི། །འབྲས་བུ་བསྐྱེད་ནས་ཟད་པར་འགྱུར་བ་ཉིད། །བྱང་ཆུབ་སེམས་ཀྱི་ལྗོན་ཤིང་རྟག་པར་ཡང་། །འབྲས་བུ་འབྱིན་པས་མི་ཟད་འཕེལ་བར་འགྱུར། །\n\nསྡིག་པ་ཤིན་ཏུ་མི་བཟད་བྱས་ན་ཡང་། །དཔའ་ལ་བརྟེན་ནས་འཇིགས་པ་ཆེན་པོ་ལྟར། །གང་ལ་བརྟེན་ནས་ཡུད་ཀྱིས་སྒྲོལ་འགྱུར་བ། །དེ་ལ་བག་ཅན་རྣམས་ཀྱིས་ཅིས་མི་བརྟེན། །\n\nདེས་ནི་དུས་མཐའི་མེ་བཞིན་སྡིག་ཆེན་རྣམས། །སྐད་ཅིག་གཅིག་གིས་ངེས་པར་སྲེག་པར་བྱེད། །\n\nདེ་ཡི་ཕན་ཡོན་དཔག་ཏུ་མེད་པ་དག །བྱམས་མགོན་བློ་དང་ལྡན་པས་ནོར་བཟང་བཤད། །\n\nབྱང་ཆུབ་སེམས་དེ་མདོར་བསྡུས་ན། །རྣམ་པ་གཉིས་སུ་ཤེས་བྱ་སྟེ། །\nབྱང་ཆུབ་སྨོན་པའི་སེམས་དང་ནི། །བྱང་ཆུབ་འཇུག་པ་ཉིད་ཡིན་ནོ། །\n\nའགྲོ་བར་འདོད་དང་འགྲོ་བ་ཡི། །བྱེ་བྲག་ཇི་ལྟར་ཤེས་པ་ལྟར། །དེ་བཞིན་མཁས་པས་འདི་གཉིས་ཀྱི། །བྱེ་བྲག་རིམ་བཞིན་ཤེས་པར་བྱ། །\n\nབྱང་ཆུབ་སྨོན་པའི་སེམས་ལས་ནི། །འཁོར་ཚེ་འབྲས་བུ་ཆེ་འབྱུང་ཡང་། །ཇི་ལྟར་འཇུག་པའི་སེམས་བཞིན་དུ། །བསོད་ནམས་རྒྱུན་ཆགས་འབྱུང་བ་མིན། །གང་ནས་བཟུང་སྟེ་སེམས་ཅན་ཁམས། །མཐའ་ཡས་རབ་ཏུ་དགྲོལ་བའི་ཕྱིར། །མི་ལྡོག་པ་ཡི་སེམས་ཀྱིས་སུ། །སེམས་དེ་ཡང་དག་བླངས་གྱུར་པ། །དེང་ནས་བཟུང་སྟེ་གཉིད་ལོག་གམ། །བག་མེད་གྱུར་ཀྱང་བསོད་ནམས་ཤུགས། །རྒྱུན་མི་འཆད་པར་དུ་མ་ཞིག །ནམ་མཁའ་མཉམ་པར་རབ་ཏུ་འབྱུང་། །\n\nའདི་ནི་འཐད་པ་དང་བཅས་པར། །ལག་བཟང་གིས་ནི་ཞུས་པ་ལས། །དམན་མོས་སེམས་ཅན་དོན་གྱི་ཕྱིར། །དེ་བཞིན་གཤེགས་པ་ཉིད་ཀྱིས་གསུངས། །\n\nསེམས་ཅན་རྣམས་ཀྱི་ཀླད་ནད་ཙམ། །བསལ་ལོ་སྙམ་དུ་བསམས་ན་ཡང་། །ཕན་འདོགས་བསམ་པ་དང་ལྡན་དེ། །བསོད་ནམས་དཔག་མེད་ལྡན་གྱུར་ན། །སེམས་ཅན་རེ་རེའི་མི་བདེ་བ། །དཔག་ཏུ་མེད་པ་བསལ་འདོད་ཅིང་། །རེ་རེའང་ཡོན་ཏན་དཔག་མེད་དུ། །བསྒྲུབ་པར་འདོད་པ་སྨོས་ཅི་དགོས། །\nཕའམ་ཡང་ན་མ་ཡང་རུང་། །སུ་ལ་འདི་འདྲའི་ཕན་སེམས་ཡོད། །ལྷ་དང་དྲང་སྲོང་རྣམས་ཀྱང་རུང་། །ཚངས་པ་ལ་ཡང་འདི་ཡོད་དམ། །\nསེམས་ཅན་དེ་དག་ཉིད་ལ་སྔོན། །རང་གི་དོན་དུ་འདི་འདྲའི་སེམས། །རྨི་ལམ་དུ་ཡང་མ་རྨིས་ན། །གཞན་གྱི་དོན་དུ་ག་ལ་སྐྱེ། །\nགཞན་དག་རང་གི་དོན་དུ་ཡང་། །མི་འབྱུང་སེམས་ཅན་དོན་སེམས་གང་། །སེམས་ཀྱི་རིན་ཆེན་ཁྱད་པར་འདི། །སྔ་ན་མེད་པའི་རྨད་ཅིག་འཁྲུངས། །\nའགྲོ་བ་ཀུན་གྱི་དགའ་བའི་རྒྱུ། །སེམས་ཅན་སྡུག་བསྔལ་རྩིར་གྱུར་པ། །རིན་ཆེན་སེམས་ཀྱི་བསོད་ནམས་གང་། །དེ་ལ་ཇི་ལྟར་གཞལ་གྱིས་ལང་། །\n\nཕན་པར་བསམས་པ་ཙམ་གྱིས་ཀྱང་། །སངས་རྒྱས་མཆོད་ལས་ཁྱད་འཕགས་ན། །སེམས་ཅན་མ་ལུས་ཐམས་ཅད་ཀྱི། །བདེ་དོན་བརྩོན་པ་སྨོས་ཅི་དགོས། །\n\nསྡུག་བསྔལ་འདོར་འདོད་སེམས་ཡོད་ཀྱང་། །སྡུག་བསྔལ་ཉིད་ལ་མངོན་པར་རྒྱུག །བདེ་བ་འདོད་ཀྱང་གཏི་མུག་པས། །རང་གི་བདེ་བ་དགྲ་ལྟར་འཇོམས། །\nགང་ཞིག་བདེ་བས་ཕོངས་པ་དང་། །སྡུག་བསྔལ་མང་ལྡན་དེ་དག་ལ། །བདེ་བ་ཀུན་གྱིས་ཚིམ་པ་དང་། །སྡུག་བསྔལ་ཐམས་ཅད་གཅོད་བྱེད་ཅིང་། །གཏི་མུག་ཀྱང་ནི་སེལ་བྱེད་པ། །དེ་དང་དགེ་མཚུངས་ག་ལ་ཡོད། །དེ་འདྲའི་བཤེས་ཀྱང་ག་ལ་ཡོད། །བསོད་ནམས་དེ་འདྲའང་ག་ལ་ཡོད། །\n\nཕན་བཏགས་ལན་ལྡོན་གང་ཡིན་པ། །དེ་ཡང་རེ་ཞིག་བསྔགས་འོས་ན། །མ་བཅོལ་ལེགས་པར་བྱེད་པ་ཡི། །བྱང་ཆུབ་སེམས་དཔའ་སྨོས་ཅི་དགོས། །\nའགྲོ་བ་ཉུང་ཟད་ནར་མའི་ཟས་སྦྱོར་བ། །སྐད་ཅིག་ཟས་ཙམ་སྦྱིན་པར་བྱེད་པ་དང་། །བརྙས་བཅས་ཉིན་ཕྱེད་འགྲངས་པར་བྱེད་པ་ཡང་། །དགེ་བ་བྱེད་པ་ཡིན་ཞེས་སྐྱེ་བོས་བཀུར། །\nསེམས་ཅན་གྲངས་མཐའ་ཡས་ལ་དུས་རིང་དུ། །བདེ་བར་གཤེགས་ཀྱི་བདེ་བ་བླ་ན་མེད། །ཡིད་ལ་བསམ་པ་མཐའ་དག་རྫོགས་བྱེད་པ། །རྟག་ཏུ་སྦྱིན་པ་ལྟ་ཞིག་སྨོས་ཅི་དགོས། །\n\nགང་ཞིག་དེ་འདྲའི་རྒྱལ་སྲས་སྦྱིན་བདག་ལ། །གལ་ཏེ་ངན་སེམས་སྐྱེད་པར་བྱེད་ན་དེ། །ངན་སེམས་བསྐྱེད་པའི་གྲངས་བཞིན་བསྐལ་པར་ནི། །དམྱལ་བར་གནས་པར་འགྱུར་ཞེས་ཐུབ་པས་གསུངས། །\nའོན་ཏེ་གང་ཞིག་ཡིད་རབ་དང་བྱེད་ན། །དེ་ཡི་འབྲས་བུ་དེ་བས་ལྷག་པར་འཕེལ། །\n\nརྒྱལ་སྲས་རྣམས་ལ་དོ་གལ་ཆེན་པོས་ཀྱང་། །སྡིག་པ་མི་འབྱུང་དགེ་བ་ངང་གིས་འཕེལ། །\nགང་ལ་སེམས་ཀྱི་དམ་པ་རིན་ཆེན་དེ། །སྐྱེས་པ་དེ་ཡི་སྐུ་ལ་ཕྱག་འཚལ་ཞིང་། །གང་ལ་གནོད་པ་བྱས་ཀྱང་བདེ་འབྲེལ་བ། །བདེ་བའི་འབྱུང་གནས་དེ་ལ་སྐྱབས་སུ་མཆི།",
    "children": [
      {
        "level": "section",
        "number": "1.1",
        "title": "Introduction to the Text",
        "verses_span": "1-4",
        "verse_text_excerpt": "བདེ་གཤེགས་ཆོས་ཀྱི་སྐུ་མངའ་སྲས་བཅས་དང་། །ཕྱག་འོས་ཀུན་ལའང་གུས་པར་ཕྱག་འཚལ་ཏེ། །\n\nབདེ་གཤེགས་སྲས་ཀྱི་སྡོམ་ལ་འཇུག་པ་ནི། །ལུང་བཞིན་མདོར་བསྡུས་ནས་ནི་བརྗོད་པར་བྱ། །\nསྔོན་ཆད་མ་བྱུང་བ་ཡང་འདིར་བརྗོད་མེད། །སྡེབ་སྦྱོར་མཁས་པའང་བདག་ལ་ཡོད་མིན་ཏེ། །དེ་ཕྱིར་གཞན་དོན་བསམ་པ་བདག་ལ་མེད། །རང་གི་ཡིད་ལ་བསྒོམ་ཕྱིར་ངས་འདི་བརྩམས། །\nདགེ་བ་བསྒོམ་ཕྱིར་བདག་གི་དད་པའི་ཤུགས། །འདི་དག་གིས་ཀྱང་རེ་ཞིག་འཕེལ་འགྱུར་ལ། །བདག་དང་སྐལ་བ་མཉམ་པ་གཞན་གྱིས་ཀྱང་། །ཅི་སྟེ་འདི་དག་མཐོང་ན་དོན་ཡོད་འགྱུར། །",
        "children": [
          {
            "level": "subsection",
            "number": "1.1.1",
            "title": "Homage",
            "verses_span": "1",
            "verse_text_excerpt": "བདེ་གཤེགས་ཆོས་ཀྱི་སྐུ་མངའ་སྲས་བཅས་དང་། །ཕྱག་འོས་ཀུན་ལའང་གུས་པར་ཕྱག་འཚལ་ཏེ། །",
            "children": []
          },
          {
            "level": "subsection",
            "number": "1.1.2",
            "title": "Author's Intention",
            "verses_span": "2-4",
            "verse_text_excerpt": "བདེ་གཤེགས་སྲས་ཀྱི་སྡོམ་ལ་འཇུག་པ་ནི། །ལུང་བཞིན་མདོར་བསྡུས་ནས་ནི་བརྗོད་པར་བྱ། །\nསྔོན་ཆད་མ་བྱུང་བ་ཡང་འདིར་བརྗོད་མེད། །སྡེབ་སྦྱོར་མཁས་པའང་བདག་ལ་ཡོད་མིན་ཏེ། །དེ་ཕྱིར་གཞན་དོན་བསམ་པ་བདག་ལ་མེད། །རང་གི་ཡིད་ལ་བསྒོམ་ཕྱིར་ངས་འདི་བརྩམས། །\nདགེ་བ་བསྒོམ་ཕྱིར་བདག་གི་དད་པའི་ཤུགས། །འདི་དག་གིས་ཀྱང་རེ་ཞིག་འཕེལ་འགྱུར་ལ། །བདག་དང་སྐལ་བ་མཉམ་པ་གཞན་གྱིས་ཀྱང་། །ཅི་སྟེ་འདི་དག་མཐོང་ན་དོན་ཡོད་འགྱུར། །",
            "children": []
          }
        ]
      },
      {
        "level": "section",
        "number": "1.2",
        "title": "Generating the Unarisen Bodhicitta and its Benefits",
        "verses_span": "5-16",
        "verse_text_excerpt": "དལ་འབྱོར་འདི་ནི་རྙེད་པར་ཤིན་ཏུ་དཀའ། །སྐྱེས་བུའི་དོན་སྒྲུབ་ཐོབ་པར་གྱུར་པ་ལ། །གལ་ཏེ་འདི་ལ་ཕན་པ་མ་བསྒྲུབས་ན། །ཕྱིས་འདི་ཡང་དག་འབྱོར་པར་ག་ལ་འགྱུར། །\n\nཇི་ལྟར་མཚན་མོ་མུན་ནག་སྤྲིན་རུམ་ན། །གློག་འགྱུ་སྐད་ཅིག་རབ་སྣང་སྟོན་པ་ལྟར། །དེ་བཞིན་སངས་རྒྱས་མཐུ་ཡིས་བརྒྱ་ལམ་ན། །འཇིག་རྟེན་བསོད་ནམས་བློ་གྲོས་ཐང་འགའ་འབྱུང་། །\n\nདེ་ལྟས་དགེ་བ་ཉམ་ཆུང་ཉིད་ལ་རྟག །སྡིག་པ་སྟོབས་ཆེན་ཤིན་ཏུ་མི་བཟད་པ། །དེ་ནི་རྫོགས་པའི་བྱང་ཆུབ་སེམས་མིན་པ། །དགེ་གཞན་གང་གིས་ཟིལ་གྱིས་གནོན་པར་འགྱུར། །\nབསྐལ་པ་དུ་མར་རབ་དགོངས་མཛད་པ་ཡི། །ཐུབ་དབང་རྣམས་ཀྱིས་འདི་ཉིད་ཕན་པར་གཟིགས། །འདིས་ནི་ཚད་མེད་སྐྱེ་བོའི་ཚོགས་རྣམས་ཀྱིས། །བདེ་མཆོག་བདེ་བླག་ཉིད་དུ་ཐོབ་པར་བྱེད། །\nསྲིད་པའི་སྡུག་བསྔལ་བརྒྱ་ཕྲག་གཞོམ་འདོད་ཅིང་། །སེམས་ཅན་མི་བདེ་བསལ་བར་འདོད་པ་དང་། །བདེ་མང་བརྒྱ་ཕྲག་སྤྱོད་པར་འདོད་པས་ཀྱང་། །བྱང་ཆུབ་སེམས་ཉིད་རྟག་ཏུ་གཏང་མི་བྱ། །\n\nབྱང་ཆུབ་སེམས་སྐྱེས་གྱུར་ན་སྐད་ཅིག་གིས། །འཁོར་བའི་བཙོན་རར་བསྡམས་པའི་ཉམ་ཐག་རྣམས། །བདེ་གཤེགས་རྣམས་ཀྱི་སྲས་ཞེས་བརྗོད་བྱ་ཞིང་། །འཇིག་རྟེན་ལྷ་མིར་བཅས་པས་ཕྱག་བྱར་འགྱུར། །\n\nགསེར་འགྱུར་རྩི་ཡི་རྣམ་པ་མཆོག་ལྟ་བུ། །མི་གཙང་ལུས་འདི་བླངས་ནས་རྒྱལ་བའི་སྐུ། །རིན་ཆེན་རིང་ཐང་མེད་པར་བསྒྱུར་བས་ན། །བྱང་ཆུབ་སེམས་ཞེས་བྱ་བ་རབ་བརྟན་ཟུང་། །\n\nའགྲོ་བའི་དེད་དཔོན་གཅིག་པུ་ཚད་མེད་བློས། །ལེགས་པར་ཡོངས་སུ་བརྟགས་ན་རིན་ཆེ་བས། །འགྲོ་བའི་གནས་དང་བྲལ་བར་འདོད་པ་རྣམས། །རིན་ཆེན་བྱང་ཆུབ་སེམས་ལེགས་བརྟན་པར་ཟུང་། །\n\nདགེ་བ་གཞན་ཀུན་ཆུ་ཤིང་བཞིན་དུ་ནི། །འབྲས་བུ་བསྐྱེད་ནས་ཟད་པར་འགྱུར་བ་ཉིད། །བྱང་ཆུབ་སེམས་ཀྱི་ལྗོན་ཤིང་རྟག་པར་ཡང་། །འབྲས་བུ་འབྱིན་པས་མི་ཟད་འཕེལ་བར་འགྱུར། །\n\nསྡིག་པ་ཤིན་ཏུ་མི་བཟད་བྱས་ན་ཡང་། །དཔའ་ལ་བརྟེན་ནས་འཇིགས་པ་ཆེན་པོ་ལྟར། །གང་ལ་བརྟེན་ནས་ཡུད་ཀྱིས་སྒྲོལ་འགྱུར་བ། །དེ་ལ་བག་ཅན་རྣམས་ཀྱིས་ཅིས་མི་བརྟེན། །\n\nདེས་ནི་དུས་མཐའི་མེ་བཞིན་སྡིག་ཆེན་རྣམས། །སྐད་ཅིག་གཅིག་གིས་ངེས་པར་སྲེག་པར་བྱེད། །\n\nདེ་ཡི་ཕན་ཡོན་དཔག་ཏུ་མེད་པ་དག །བྱམས་མགོན་བློ་དང་ལྡན་པས་ནོར་བཟང་བཤད། །",
        "children": [
          {
            "level": "subsection",
            "number": "1.2.1",
            "title": "The Basis of Bodhicitta",
            "verses_span": "5-6",
            "verse_text_excerpt": "དལ་འབྱོར་འདི་ནི་རྙེད་པར་ཤིན་ཏུ་དཀའ། །སྐྱེས་བུའི་དོན་སྒྲུབ་ཐོབ་པར་གྱུར་པ་ལ། །གལ་ཏེ་འདི་ལ་ཕན་པ་མ་བསྒྲུབས་ན། །ཕྱིས་འདི་ཡང་དག་འབྱོར་པར་ག་ལ་འགྱུར། །\n\nཇི་ལྟར་མཚན་མོ་མུན་ནག་སྤྲིན་རུམ་ན། །གློག་འགྱུ་སྐད་ཅིག་རབ་སྣང་སྟོན་པ་ལྟར། །དེ་བཞིན་སངས་རྒྱས་མཐུ་ཡིས་བརྒྱ་ལམ་ན། །འཇིག་རྟེན་བསོད་ནམས་བློ་གྲོས་ཐང་འགའ་འབྱུང་། །",
            "children": [
              {
                "level": "sub-subsection",
                "number": "1.2.1.1",
                "title": "The Precious Human Body",
                "verses_span": "5",
                "verse_text_excerpt": "དལ་འབྱོར་འདི་ནི་རྙེད་པར་ཤིན་ཏུ་དཀའ། །སྐྱེས་བུའི་དོན་སྒྲུབ་ཐོབ་པར་གྱུར་པ་ལ། །གལ་ཏེ་འདི་ལ་ཕན་པ་མ་བསྒྲུབས་ན། །ཕྱིས་འདི་ཡང་དག་འབྱོར་པར་ག་ལ་འགྱུར། །",
                "children": []
              },
              {
                "level": "sub-subsection",
                "number": "1.2.1.2",
                "title": "Rarity of Aspiration for Virtue",
                "verses_span": "6",
                "verse_text_excerpt": "ཇི་ལྟར་མཚན་མོ་མུན་ནག་སྤྲིན་རུམ་ན། །གློག་འགྱུ་སྐད་ཅིག་རབ་སྣང་སྟོན་པ་ལྟར། །དེ་བཞིན་སངས་རྒྱས་མཐུ་ཡིས་བརྒྱ་ལམ་ན། །འཇིག་རྟེན་བསོད་ནམས་བློ་གྲོས་ཐང་འགའ་འབྱུང་། །",
                "children": []
              }
            ]
          },
          {
            "level": "subsection",
            "number": "1.2.2",
            "title": "General Benefits of Bodhicitta",
            "verses_span": "7-16",
            "verse_text_excerpt": "དེ་ལྟས་དགེ་བ་ཉམ་ཆུང་ཉིད་ལ་རྟག །སྡིག་པ་སྟོབས་ཆེན་ཤིན་ཏུ་མི་བཟད་པ། །དེ་ནི་རྫོགས་པའི་བྱང་ཆུབ་སེམས་མིན་པ། །དགེ་གཞན་གང་གིས་ཟིལ་གྱིས་གནོན་པར་འགྱུར། །\nབསྐལ་པ་དུ་མར་རབ་དགོངས་མཛད་པ་ཡི། །ཐུབ་དབང་རྣམས་ཀྱིས་འདི་ཉིད་ཕན་པར་གཟིགས། །འདིས་ནི་ཚད་མེད་སྐྱེ་བོའི་ཚོགས་རྣམས་ཀྱིས། །བདེ་མཆོག་བདེ་བླག་ཉིད་དུ་ཐོབ་པར་བྱེད། །\nསྲིད་པའི་སྡུག་བསྔལ་བརྒྱ་ཕྲག་གཞོམ་འདོད་ཅིང་། །སེམས་ཅན་མི་བདེ་བསལ་བར་འདོད་པ་དང་། །བདེ་མང་བརྒྱ་ཕྲག་སྤྱོད་པར་འདོད་པས་ཀྱང་། །བྱང་ཆུབ་སེམས་ཉིད་རྟག་ཏུ་གཏང་མི་བྱ། །\n\nབྱང་ཆུབ་སེམས་སྐྱེས་གྱུར་ན་སྐད་ཅིག་གིས། །འཁོར་བའི་བཙོན་རར་བསྡམས་པའི་ཉམ་ཐག་རྣམས། །བདེ་གཤེགས་རྣམས་ཀྱི་སྲས་ཞེས་བརྗོད་བྱ་ཞིང་། །འཇིག་རྟེན་ལྷ་མིར་བཅས་པས་ཕྱག་བྱར་འགྱུར། །\n\nགསེར་འགྱུར་རྩི་ཡི་རྣམ་པ་མཆོག་ལྟ་བུ། །མི་གཙང་ལུས་འདི་བླངས་ནས་རྒྱལ་བའི་སྐུ། །རིན་ཆེན་རིང་ཐང་མེད་པར་བསྒྱུར་བས་ན། །བྱང་ཆུབ་སེམས་ཞེས་བྱ་བ་རབ་བརྟན་ཟུང་། །\n\nའགྲོ་བའི་དེད་དཔོན་གཅིག་པུ་ཚད་མེད་བློས། །ལེགས་པར་ཡོངས་སུ་བརྟགས་ན་རིན་ཆེ་བས། །འགྲོ་བའི་གནས་དང་བྲལ་བར་འདོད་པ་རྣམས། །རིན་ཆེན་བྱང་ཆུབ་སེམས་ལེགས་བརྟན་པར་ཟུང་། །\n\nདགེ་བ་གཞན་ཀུན་ཆུ་ཤིང་བཞིན་དུ་ནི། །འབྲས་བུ་བསྐྱེད་ནས་ཟད་པར་འགྱུར་བ་ཉིད། །བྱང་ཆུབ་སེམས་ཀྱི་ལྗོན་ཤིང་རྟག་པར་ཡང་། །འབྲས་བུ་འབྱིན་པས་མི་ཟད་འཕེལ་བར་འགྱུར། །\n\nསྡིག་པ་ཤིན་ཏུ་མི་བཟད་བྱས་ན་ཡང་། །དཔའ་ལ་བརྟེན་ནས་འཇིགས་པ་ཆེན་པོ་ལྟར། །གང་ལ་བརྟེན་ནས་ཡུད་ཀྱིས་སྒྲོལ་འགྱུར་བ། །དེ་ལ་བག་ཅན་རྣམས་ཀྱིས་ཅིས་མི་བརྟེན། །\n\nདེས་ནི་དུས་མཐའི་མེ་བཞིན་སྡིག་ཆེན་རྣམས། །སྐད་ཅིག་གཅིག་གིས་ངེས་པར་སྲེག་པར་བྱེད། །\n\nདེ་ཡི་ཕན་ཡོན་དཔག་ཏུ་མེད་པ་དག །བྱམས་མགོན་བློ་དང་ལྡན་པས་ནོར་བཟང་བཤད། །",
            "children": [
              {
                "level": "sub-subsection",
                "number": "1.2.2.1",
                "title": "Benefits Superior to Other Virtues",
                "verses_span": "7-9",
                "verse_text_excerpt": "དེ་ལྟས་དགེ་བ་ཉམ་ཆུང་ཉིད་ལ་རྟག །སྡིག་པ་སྟོབས་ཆེན་ཤིན་ཏུ་མི་བཟད་པ། །དེ་ནི་རྫོགས་པའི་བྱང་ཆུབ་སེམས་མིན་པ། །དགེ་གཞན་གང་གིས་ཟིལ་གྱིས་གནོན་པར་འགྱུར། །\nབསྐལ་པ་དུ་མར་རབ་དགོངས་མཛད་པ་ཡི། །ཐུབ་དབང་རྣམས་ཀྱིས་འདི་ཉིད་ཕན་པར་གཟིགས། །འདིས་ནི་ཚད་མེད་སྐྱེ་བོའི་ཚོགས་རྣམས་ཀྱིས། །བདེ་མཆོག་བདེ་བླག་ཉིད་དུ་ཐོབ་པར་བྱེད། །\nསྲིད་པའི་སྡུག་བསྔལ་བརྒྱ་ཕྲག་གཞོམ་འདོད་ཅིང་། །སེམས་ཅན་མི་བདེ་བསལ་བར་འདོད་པ་དང་། །བདེ་མང་བརྒྱ་ཕྲག་སྤྱོད་པར་འདོད་པས་ཀྱང་། །བྱང་ཆུབ་སེམས་ཉིད་རྟག་ཏུ་གཏང་མི་བྱ། །",
                "children": []
              },
              {
                "level": "sub-subsection",
                "number": "1.2.2.2",
                "title": "Benefits of Changing Name and Meaning",
                "verses_span": "10",
                "verse_text_excerpt": "བྱང་ཆུབ་སེམས་སྐྱེས་གྱུར་ན་སྐད་ཅིག་གིས། །འཁོར་བའི་བཙོན་རར་བསྡམས་པའི་ཉམ་ཐག་རྣམས། །བདེ་གཤེགས་རྣམས་ཀྱི་སྲས་ཞེས་བརྗོད་བྱ་ཞིང་། །འཇིག་རྟེན་ལྷ་མིར་བཅས་པས་ཕྱག་བྱར་འགྱུར། །",
                "children": []
              },
              {
                "level": "sub-subsection",
                "number": "1.2.2.3",
                "title": "Benefits Shown Through Examples",
                "verses_span": "11-16",
                "verse_text_excerpt": "གསེར་འགྱུར་རྩི་ཡི་རྣམ་པ་མཆོག་ལྟ་བུ། །མི་གཙང་ལུས་འདི་བླངས་ནས་རྒྱལ་བའི་སྐུ། །རིན་ཆེན་རིང་ཐང་མེད་པར་བསྒྱུར་བས་ན། །བྱང་ཆུབ་སེམས་ཞེས་བྱ་བ་རབ་བརྟན་ཟུང་། །\n\nའགྲོ་བའི་དེད་དཔོན་གཅིག་པུ་ཚད་མེད་བློས། །ལེགས་པར་ཡོངས་སུ་བརྟགས་ན་རིན་ཆེ་བས། །འགྲོ་བའི་གནས་དང་བྲལ་བར་འདོད་པ་རྣམས། །རིན་ཆེན་བྱང་ཆུབ་སེམས་ལེགས་བརྟན་པར་ཟུང་། །\n\nདགེ་བ་གཞན་ཀུན་ཆུ་ཤིང་བཞིན་དུ་ནི། །འབྲས་བུ་བསྐྱེད་ནས་ཟད་པར་འགྱུར་བ་ཉིད། །བྱང་ཆུབ་སེམས་ཀྱི་ལྗོན་ཤིང་རྟག་པར་ཡང་། །འབྲས་བུ་འབྱིན་པས་མི་ཟད་འཕེལ་བར་འགྱུར། །\n\nསྡིག་པ་ཤིན་ཏུ་མི་བཟད་བྱས་ན་ཡང་། །དཔའ་ལ་བརྟེན་ནས་འཇིགས་པ་ཆེན་པོ་ལྟར། །གང་ལ་བརྟེན་ནས་ཡུད་ཀྱིས་སྒྲོལ་འགྱུར་བ། །དེ་ལ་བག་ཅན་རྣམས་ཀྱིས་ཅིས་མི་བརྟེན། །\n\nདེས་ནི་དུས་མཐའི་མེ་བཞིན་སྡིག་ཆེན་རྣམས། །སྐད་ཅིག་གཅིག་གིས་ངེས་པར་སྲེག་པར་བྱེད། །\n\nདེ་ཡི་ཕན་ཡོན་དཔག་ཏུ་མེད་པ་དག །བྱམས་མགོན་བློ་དང་ལྡན་པས་ནོར་བཟང་བཤད། །",
                "children": [
                  {
                    "level": "sub-sub-subsection",
                    "number": "1.2.2.3.1",
                    "title": "Example of Alchemical Elixir",
                    "verses_span": "11",
                    "verse_text_excerpt": "གསེར་འགྱུར་རྩི་ཡི་རྣམ་པ་མཆོག་ལྟ་བུ། །མི་གཙང་ལུས་འདི་བླངས་ནས་རྒྱལ་བའི་སྐུ། །རིན་ཆེན་རིང་ཐང་མེད་པར་བསྒྱུར་བས་ན། །བྱང་ཆུབ་སེམས་ཞེས་བྱ་བ་རབ་བརྟན་ཟུང་། །",
                    "children": []
                  },
                  {
                    "level": "sub-sub-subsection",
                    "number": "1.2.2.3.2",
                    "title": "Example of a Jewel",
                    "verses_span": "12",
                    "verse_text_excerpt": "འགྲོ་བའི་དེད་དཔོན་གཅིག་པུ་ཚད་མེད་བློས། །ལེགས་པར་ཡོངས་སུ་བརྟགས་ན་རིན་ཆེ་བས། །འགྲོ་བའི་གནས་དང་བྲལ་བར་འདོད་པ་རྣམས། །རིན་ཆེན་བྱང་ཆུབ་སེམས་ལེགས་བརྟན་པར་ཟུང་། །",
                    "children": []
                  },
                  {
                    "level": "sub-sub-subsection",
                    "number": "1.2.2.3.3",
                    "title": "Example of a Fruit-bearing Tree",
                    "verses_span": "13",
                    "verse_text_excerpt": "དགེ་བ་གཞན་ཀུན་ཆུ་ཤིང་བཞིན་དུ་ནི། །འབྲས་བུ་བསྐྱེད་ནས་ཟད་པར་འགྱུར་བ་ཉིད། །བྱང་ཆུབ་སེམས་ཀྱི་ལྗོན་ཤིང་རྟག་པར་ཡང་། །འབྲས་བུ་འབྱིན་པས་མི་ཟད་འཕེལ་བར་འགྱུར། །",
                    "children": []
                  },
                  {
                    "level": "sub-sub-subsection",
                    "number": "1.2.2.3.4",
                    "title": "Example of a Brave Escort",
                    "verses_span": "14",
                    "verse_text_excerpt": "སྡིག་པ་ཤིན་ཏུ་མི་བཟད་བྱས་ན་ཡང་། །དཔའ་ལ་བརྟེན་ནས་འཇིགས་པ་ཆེན་པོ་ལྟར། །གང་ལ་བརྟེན་ནས་ཡུད་ཀྱིས་སྒྲོལ་འགྱུར་བ། །དེ་ལ་བག་ཅན་རྣམས་ཀྱིས་ཅིས་མི་བརྟེན། །",
                    "children": []
                  },
                  {
                    "level": "sub-sub-subsection",
                    "number": "1.2.2.3.5",
                    "title": "Example of the Fire at the End of Time",
                    "verses_span": "15",
                    "verse_text_excerpt": "དེས་ནི་དུས་མཐའི་མེ་བཞིན་སྡིག་ཆེན་རྣམས། །སྐད་ཅིག་གཅིག་གིས་ངེས་པར་སྲེག་པར་བྱེད། །",
                    "children": []
                  },
                  {
                    "level": "sub-sub-subsection",
                    "number": "1.2.2.3.6",
                    "title": "Reference to Other Texts",
                    "verses_span": "16",
                    "verse_text_excerpt": "དེ་ཡི་ཕན་ཡོན་དཔག་ཏུ་མེད་པ་དག །བྱམས་མགོན་བློ་དང་ལྡན་པས་ནོར་བཟང་བཤད། །",
                    "children": []
                  }
                ]
              }
            ]
          }
        ]
      },
      {
        "level": "section",
        "number": "1.3",
        "title": "Distinction between Aspiration and Engagement Bodhicitta",
        "verses_span": "17-29",
        "verse_text_excerpt": "བྱང་ཆུབ་སེམས་དེ་མདོར་བསྡུས་ན། །རྣམ་པ་གཉིས་སུ་ཤེས་བྱ་སྟེ། །\nབྱང་ཆུབ་སྨོན་པའི་སེམས་དང་ནི། །བྱང་ཆུབ་འཇུག་པ་ཉིད་ཡིན་ནོ། །\n\nའགྲོ་བར་འདོད་དང་འགྲོ་བ་ཡི། །བྱེ་བྲག་ཇི་ལྟར་ཤེས་པ་ལྟར། །དེ་བཞིན་མཁས་པས་འདི་གཉིས་ཀྱི། །བྱེ་བྲག་རིམ་བཞིན་ཤེས་པར་བྱ། །\n\nབྱང་ཆུབ་སྨོན་པའི་སེམས་ལས་ནི། །འཁོར་ཚེ་འབྲས་བུ་ཆེ་འབྱུང་ཡང་། །ཇི་ལྟར་འཇུག་པའི་སེམས་བཞིན་དུ། །བསོད་ནམས་རྒྱུན་ཆགས་འབྱུང་བ་མིན། །གང་ནས་བཟུང་སྟེ་སེམས་ཅན་ཁམས། །མཐའ་ཡས་རབ་ཏུ་དགྲོལ་བའི་ཕྱིར། །མི་ལྡོག་པ་ཡི་སེམས་ཀྱིས་སུ། །སེམས་དེ་ཡང་དག་བླངས་གྱུར་པ། །དེང་ནས་བཟུང་སྟེ་གཉིད་ལོག་གམ། །བག་མེད་གྱུར་ཀྱང་བསོད་ནམས་ཤུགས། །རྒྱུན་མི་འཆད་པར་དུ་མ་ཞིག །ནམ་མཁའ་མཉམ་པར་རབ་ཏུ་འབྱུང་། །\n\nའདི་ནི་འཐད་པ་དང་བཅས་པར། །ལག་བཟང་གིས་ནི་ཞུས་པ་ལས། །དམན་མོས་སེམས་ཅན་དོན་གྱི་ཕྱིར། །དེ་བཞིན་གཤེགས་པ་ཉིད་ཀྱིས་གསུངས། །\n\nསེམས་ཅན་རྣམས་ཀྱི་ཀླད་ནད་ཙམ། །བསལ་ལོ་སྙམ་དུ་བསམས་ན་ཡང་། །ཕན་འདོགས་བསམ་པ་དང་ལྡན་དེ། །བསོད་ནམས་དཔག་མེད་ལྡན་གྱུར་ན། །སེམས་ཅན་རེ་རེའི་མི་བདེ་བ། །དཔག་ཏུ་མེད་པ་བསལ་འདོད་ཅིང་། །རེ་རེའང་ཡོན་ཏན་དཔག་མེད་དུ། །བསྒྲུབ་པར་འདོད་པ་སྨོས་ཅི་དགོས། །\nཕའམ་ཡང་ན་མ་ཡང་རུང་། །སུ་ལ་འདི་འདྲའི་ཕན་སེམས་ཡོད། །ལྷ་དང་དྲང་སྲོང་རྣམས་ཀྱང་རུང་། །ཚངས་པ་ལ་ཡང་འདི་ཡོད་དམ། །\nསེམས་ཅན་དེ་དག་ཉིད་ལ་སྔོན། །རང་གི་དོན་དུ་འདི་འདྲའི་སེམས། །རྨི་ལམ་དུ་ཡང་མ་རྨིས་ན། །གཞན་གྱི་དོན་དུ་ག་ལ་སྐྱེ། །\nགཞན་དག་རང་གི་དོན་དུ་ཡང་། །མི་འབྱུང་སེམས་ཅན་དོན་སེམས་གང་། །སེམས་ཀྱི་རིན་ཆེན་ཁྱད་པར་འདི། །སྔ་ན་མེད་པའི་རྨད་ཅིག་འཁྲུངས། །\nའགྲོ་བ་ཀུན་གྱི་དགའ་བའི་རྒྱུ། །སེམས་ཅན་སྡུག་བསྔལ་རྩིར་གྱུར་པ། །རིན་ཆེན་སེམས་ཀྱི་བསོད་ནམས་གང་། །དེ་ལ་ཇི་ལྟར་གཞལ་གྱིས་ལང་། །\n\nཕན་པར་བསམས་པ་ཙམ་གྱིས་ཀྱང་། །སངས་རྒྱས་མཆོད་ལས་ཁྱད་འཕགས་ན། །སེམས་ཅན་མ་ལུས་ཐམས་ཅད་ཀྱི། །བདེ་དོན་བརྩོན་པ་སྨོས་ཅི་དགོས། །\n\nསྡུག་བསྔལ་འདོར་འདོད་སེམས་ཡོད་ཀྱང་། །སྡུག་བསྔལ་ཉིད་ལ་མངོན་པར་རྒྱུག །བདེ་བ་འདོད་ཀྱང་གཏི་མུག་པས། །རང་གི་བདེ་བ་དགྲ་ལྟར་འཇོམས། །\nགང་ཞིག་བདེ་བས་ཕོངས་པ་དང་། །སྡུག་བསྔལ་མང་ལྡན་དེ་དག་ལ། །བདེ་བ་ཀུན་གྱིས་ཚིམ་པ་དང་། །སྡུག་བསྔལ་ཐམས་ཅད་གཅོད་བྱེད་ཅིང་། །གཏི་མུག་ཀྱང་ནི་སེལ་བྱེད་པ། །དེ་དང་དགེ་མཚུངས་ག་ལ་ཡོད། །དེ་འདྲའི་བཤེས་ཀྱང་ག་ལ་ཡོད། །བསོད་ནམས་དེ་འདྲའང་ག་ལ་ཡོད། །",
        "children": [
          {
            "level": "subsection",
            "number": "1.3.1",
            "title": "Distinction between Aspiration and Engagement",
            "verses_span": "17-19",
            "verse_text_excerpt": "བྱང་ཆུབ་སེམས་དེ་མདོར་བསྡུས་ན། །རྣམ་པ་གཉིས་སུ་ཤེས་བྱ་སྟེ། །\nབྱང་ཆུབ་སྨོན་པའི་སེམས་དང་ནི། །བྱང་ཆུབ་འཇུག་པ་ཉིད་ཡིན་ནོ། །\n\nའགྲོ་བར་འདོད་དང་འགྲོ་བ་ཡི། །བྱེ་བྲག་ཇི་ལྟར་ཤེས་པ་ལྟར། །དེ་བཞིན་མཁས་པས་འདི་གཉིས་ཀྱི། །བྱེ་བྲག་རིམ་བཞིན་ཤེས་པར་བྱ། །",
            "children": [
              {
                "level": "sub-subsection",
                "number": "1.3.1.1",
                "title": "Two Kinds of Bodhicitta",
                "verses_span": "17-18",
                "verse_text_excerpt": "བྱང་ཆུབ་སེམས་དེ་མདོར་བསྡུས་ན། །རྣམ་པ་གཉིས་སུ་ཤེས་བྱ་སྟེ། །\nབྱང་ཆུབ་སྨོན་པའི་སེམས་དང་ནི། །བྱང་ཆུབ་འཇུག་པ་ཉིད་ཡིན་ནོ། །",
                "children": []
              },
              {
                "level": "sub-subsection",
                "number": "1.3.1.2",
                "title": "Analogy for Distinction",
                "verses_span": "19",
                "verse_text_excerpt": "འགྲོ་བར་འདོད་དང་འགྲོ་བ་ཡི། །བྱེ་བྲག་ཇི་ལྟར་ཤེས་པ་ལྟར། །དེ་བཞིན་མཁས་པས་འདི་གཉིས་ཀྱི། །བྱེ་བྲག་རིམ་བཞིན་ཤེས་པར་བྱ། །",
                "children": []
              }
            ]
          },
          {
            "level": "subsection",
            "number": "1.3.2",
            "title": "Difference in Benefits",
            "verses_span": "20",
            "verse_text_excerpt": "བྱང་ཆུབ་སྨོན་པའི་སེམས་ལས་ནི། །འཁོར་ཚེ་འབྲས་བུ་ཆེ་འབྱུང་ཡང་། །ཇི་ལྟར་འཇུག་པའི་སེམས་བཞིན་དུ། །བསོད་ནམས་རྒྱུན་ཆགས་འབྱུང་བ་མིན། །གང་ནས་བཟུང་སྟེ་སེམས་ཅན་ཁམས། །མཐའ་ཡས་རབ་ཏུ་དགྲོལ་བའི་ཕྱིར། །མི་ལྡོག་པ་ཡི་སེམས་ཀྱིས་སུ། །སེམས་དེ་ཡང་དག་བླངས་གྱུར་པ། །དེང་ནས་བཟུང་སྟེ་གཉིད་ལོག་གམ། །བག་མེད་གྱུར་ཀྱང་བསོད་ནམས་ཤུགས། །རྒྱུན་མི་འཆད་པར་དུ་མ་ཞིག །ནམ་མཁའ་མཉམ་པར་རབ་ཏུ་འབྱུང་། །",
            "children": []
          },
          {
            "level": "subsection",
            "number": "1.3.3",
            "title": "Establishing through Scripture and Reasoning",
            "verses_span": "21-29",
            "verse_text_excerpt": "འདི་ནི་འཐད་པ་དང་བཅས་པར། །ལག་བཟང་གིས་ནི་ཞུས་པ་ལས། །དམན་མོས་སེམས་ཅན་དོན་གྱི་ཕྱིར། །དེ་བཞིན་གཤེགས་པ་ཉིད་ཀྱིས་གསུངས། །\n\nསེམས་ཅན་རྣམས་ཀྱི་ཀླད་ནད་ཙམ། །བསལ་ལོ་སྙམ་དུ་བསམས་ན་ཡང་། །ཕན་འདོགས་བསམ་པ་དང་ལྡན་དེ། །བསོད་ནམས་དཔག་མེད་ལྡན་གྱུར་ན། །སེམས་ཅན་རེ་རེའི་མི་བདེ་བ། །དཔག་ཏུ་མེད་པ་བསལ་འདོད་ཅིང་། །རེ་རེའང་ཡོན་ཏན་དཔག་མེད་དུ། །བསྒྲུབ་པར་འདོད་པ་སྨོས་ཅི་དགོས། །\nཕའམ་ཡང་ན་མ་ཡང་རུང་། །སུ་ལ་འདི་འདྲའི་ཕན་སེམས་ཡོད། །ལྷ་དང་དྲང་སྲོང་རྣམས་ཀྱང་རུང་། །ཚངས་པ་ལ་ཡང་འདི་ཡོད་དམ། །\nསེམས་ཅན་དེ་དག་ཉིད་ལ་སྔོན། །རང་གི་དོན་དུ་འདི་འདྲའི་སེམས། །རྨི་ལམ་དུ་ཡང་མ་རྨིས་ན། །གཞན་གྱི་དོན་དུ་ག་ལ་སྐྱེ། །\nགཞན་དག་རང་གི་དོན་དུ་ཡང་། །མི་འབྱུང་སེམས་ཅན་དོན་སེམས་གང་། །སེམས་ཀྱི་རིན་ཆེན་ཁྱད་པར་འདི། །སྔ་ན་མེད་པའི་རྨད་ཅིག་འཁྲུངས། །\nའགྲོ་བ་ཀུན་གྱི་དགའ་བའི་རྒྱུ། །སེམས་ཅན་སྡུག་བསྔལ་རྩིར་གྱུར་པ། །རིན་ཆེན་སེམས་ཀྱི་བསོད་ནམས་གང་། །དེ་ལ་ཇི་ལྟར་གཞལ་གྱིས་ལང་། །\n\nཕན་པར་བསམས་པ་ཙམ་གྱིས་ཀྱང་། །སངས་རྒྱས་མཆོད་ལས་ཁྱད་འཕགས་ན། །སེམས་ཅན་མ་ལུས་ཐམས་ཅད་ཀྱི། །བདེ་དོན་བརྩོན་པ་སྨོས་ཅི་དགོས། །\n\nསྡུག་བསྔལ་འདོར་འདོད་སེམས་ཡོད་ཀྱང་། །སྡུག་བསྔལ་ཉིད་ལ་མངོན་པར་རྒྱུག །བདེ་བ་འདོད་ཀྱང་གཏི་མུག་པས། །རང་གི་བདེ་བ་དགྲ་ལྟར་འཇོམས། །\nགང་ཞིག་བདེ་བས་ཕོངས་པ་དང་། །སྡུག་བསྔལ་མང་ལྡན་དེ་དག་ལ། །བདེ་བ་ཀུན་གྱིས་ཚིམ་པ་དང་། །སྡུག་བསྔལ་ཐམས་ཅད་གཅོད་བྱེད་ཅིང་། །གཏི་མུག་ཀྱང་ནི་སེལ་བྱེད་པ། །དེ་དང་དགེ་མཚུངས་ག་ལ་ཡོད། །དེ་འདྲའི་བཤེས་ཀྱང་ག་ལ་ཡོད། །བསོད་ནམས་དེ་འདྲའང་ག་ལ་ཡོད། །",
            "children": [
              {
                "level": "sub-subsection",
                "number": "1.3.3.1",
                "title": "Establishing through Scripture",
                "verses_span": "21",
                "verse_text_excerpt": "འདི་ནི་འཐད་པ་དང་བཅས་པར། །ལག་བཟང་གིས་ནི་ཞུས་པ་ལས། །དམན་མོས་སེམས་ཅན་དོན་གྱི་ཕྱིར། །དེ་བཞིན་གཤེགས་པ་ཉིད་ཀྱིས་གསུངས། །",
                "children": []
              },
              {
                "level": "sub-subsection",
                "number": "1.3.3.2",
                "title": "Establishing through Reasoning",
                "verses_span": "22-29",
                "verse_text_excerpt": "སེམས་ཅན་རྣམས་ཀྱི་ཀླད་ནད་ཙམ། །བསལ་ལོ་སྙམ་དུ་བསམས་ན་ཡང་། །ཕན་འདོགས་བསམ་པ་དང་ལྡན་དེ། །བསོད་ནམས་དཔག་མེད་ལྡན་གྱུར་ན། །སེམས་ཅན་རེ་རེའི་མི་བདེ་བ། །དཔག་ཏུ་མེད་པ་བསལ་འདོད་ཅིང་། །རེ་རེའང་ཡོན་ཏན་དཔག་མེད་དུ། །བསྒྲུབ་པར་འདོད་པ་སྨོས་ཅི་དགོས། །\nཕའམ་ཡང་ན་མ་ཡང་རུང་། །སུ་ལ་འདི་འདྲའི་ཕན་སེམས་ཡོད། །ལྷ་དང་དྲང་སྲོང་རྣམས་ཀྱང་རུང་། །ཚངས་པ་ལ་ཡང་འདི་ཡོད་དམ། །\nསེམས་ཅན་དེ་དག་ཉིད་ལ་སྔོན། །རང་གི་དོན་དུ་འདི་འདྲའི་སེམས། །རྨི་ལམ་དུ་ཡང་མ་རྨིས་ན། །གཞན་གྱི་དོན་དུ་ག་ལ་སྐྱེ། །\nགཞན་དག་རང་གི་དོན་དུ་ཡང་། །མི་འབྱུང་སེམས་ཅན་དོན་སེམས་གང་། །སེམས་ཀྱི་རིན་ཆེན་ཁྱད་པར་འདི། །སྔ་ན་མེད་པའི་རྨད་ཅིག་འཁྲུངས། །\nའགྲོ་བ་ཀུན་གྱི་དགའ་བའི་རྒྱུ། །སེམས་ཅན་སྡུག་བསྔལ་རྩིར་གྱུར་པ། །རིན་ཆེན་སེམས་ཀྱི་བསོད་ནམས་གང་། །དེ་ལ་ཇི་ལྟར་གཞལ་གྱིས་ལང་། །\n\nཕན་པར་བསམས་པ་ཙམ་གྱིས་ཀྱང་། །སངས་རྒྱས་མཆོད་ལས་ཁྱད་འཕགས་ན། །སེམས་ཅན་མ་ལུས་ཐམས་ཅད་ཀྱི། །བདེ་དོན་བརྩོན་པ་སྨོས་ཅི་དགོས། །\n\nསྡུག་བསྔལ་འདོར་འདོད་སེམས་ཡོད་ཀྱང་། །སྡུག་བསྔལ་ཉིད་ལ་མངོན་པར་རྒྱུག །བདེ་བ་འདོད་ཀྱང་གཏི་མུག་པས། །རང་གི་བདེ་བ་དགྲ་ལྟར་འཇོམས། །\nགང་ཞིག་བདེ་བས་ཕོངས་པ་དང་། །སྡུག་བསྔལ་མང་ལྡན་དེ་དག་ལ། །བདེ་བ་ཀུན་གྱིས་ཚིམ་པ་དང་། །སྡུག་བསྔལ་ཐམས་ཅད་གཅོད་བྱེད་ཅིང་། །གཏི་མུག་ཀྱང་ནི་སེལ་བྱེད་པ། །དེ་དང་དགེ་མཚུངས་ག་ལ་ཡོད། །དེ་འདྲའི་བཤེས་ཀྱང་ག་ལ་ཡོད། །བསོད་ནམས་དེ་འདྲའང་ག་ལ་ཡོད། །",
                "children": [
                  {
                    "level": "sub-sub-subsection",
                    "number": "1.3.3.2.1",
                    "title": "Superiority of Bodhicitta's Intention",
                    "verses_span": "22-26",
                    "verse_text_excerpt": "སེམས་ཅན་རྣམས་ཀྱི་ཀླད་ནད་ཙམ། །བསལ་ལོ་སྙམ་དུ་བསམས་ན་ཡང་། །ཕན་འདོགས་བསམ་པ་དང་ལྡན་དེ། །བསོད་ནམས་དཔག་མེད་ལྡན་གྱུར་ན། །སེམས་ཅན་རེ་རེའི་མི་བདེ་བ། །དཔག་ཏུ་མེད་པ་བསལ་འདོད་ཅིང་། །རེ་རེའང་ཡོན་ཏན་དཔག་མེད་དུ། །བསྒྲུབ་པར་འདོད་པ་སྨོས་ཅི་དགོས། །\nཕའམ་ཡང་ན་མ་ཡང་རུང་། །སུ་ལ་འདི་འདྲའི་ཕན་སེམས་ཡོད། །ལྷ་དང་དྲང་སྲོང་རྣམས་ཀྱང་རུང་། །ཚངས་པ་ལ་ཡང་འདི་ཡོད་དམ། །\nསེམས་ཅན་དེ་དག་ཉིད་ལ་སྔོན། །རང་གི་དོན་དུ་འདི་འདྲའི་སེམས། །རྨི་ལམ་དུ་ཡང་མ་རྨིས་ན། །གཞན་གྱི་དོན་དུ་ག་ལ་སྐྱེ། །\nགཞན་དག་རང་གི་དོན་དུ་ཡང་། །མི་འབྱུང་སེམས་ཅན་དོན་སེམས་གང་། །སེམས་ཀྱི་རིན་ཆེན་ཁྱད་པར་འདི། །སྔ་ན་མེད་པའི་རྨད་ཅིག་འཁྲུངས། །\nའགྲོ་བ་ཀུན་གྱི་དགའ་བའི་རྒྱུ། །སེམས་ཅན་སྡུག་བསྔལ་རྩིར་གྱུར་པ། །རིན་ཆེན་སེམས་ཀྱི་བསོད་ནམས་གང་། །དེ་ལ་ཇི་ལྟར་གཞལ་གྱིས་ལང་། །",
                    "children": []
                  },
                  {
                    "level": "sub-sub-subsection",
                    "number": "1.3.3.2.2",
                    "title": "Comparison with Offering to Buddhas",
                    "verses_span": "27",
                    "verse_text_excerpt": "ཕན་པར་བསམས་པ་ཙམ་གྱིས་ཀྱང་། །སངས་རྒྱས་མཆོད་ལས་ཁྱད་འཕགས་ན། །སེམས་ཅན་མ་ལུས་ཐམས་ཅད་ཀྱི། །བདེ་དོན་བརྩོན་པ་སྨོས་ཅི་དགོས། །",
                    "children": []
                  },
                  {
                    "level": "sub-sub-subsection",
                    "number": "1.3.3.2.3",
                    "title": "Ignorance and Suffering",
                    "verses_span": "28-29",
                    "verse_text_excerpt": "སྡུག་བསྔལ་འདོར་འདོད་སེམས་ཡོད་ཀྱང་། །སྡུག་བསྔལ་ཉིད་ལ་མངོན་པར་རྒྱུག །བདེ་བ་འདོད་ཀྱང་གཏི་མུག་པས། །རང་གི་བདེ་བ་དགྲ་ལྟར་འཇོམས། །\nགང་ཞིག་བདེ་བས་ཕོངས་པ་དང་། །སྡུག་བསྔལ་མང་ལྡན་དེ་དག་ལ། །བདེ་བ་ཀུན་གྱིས་ཚིམ་པ་དང་། །སྡུག་བསྔལ་ཐམས་ཅད་གཅོད་བྱེད་ཅིང་། །གཏི་མུག་ཀྱང་ནི་སེལ་བྱེད་པ། །དེ་དང་དགེ་མཚུངས་ག་ལ་ཡོད། །དེ་འདྲའི་བཤེས་ཀྱང་ག་ལ་ཡོད། །བསོད་ནམས་དེ་འདྲའང་ག་ལ་ཡོད། །",
                    "children": []
                  }
                ]
              }
            ]
          }
        ]
      },
      {
        "level": "section",
        "number": "1.4",
        "title": "Greatness of the Person Endowed with Bodhicitta",
        "verses_span": "30-36",
        "verse_text_excerpt": "ཕན་བཏགས་ལན་ལྡོན་གང་ཡིན་པ། །དེ་ཡང་རེ་ཞིག་བསྔགས་འོས་ན། །མ་བཅོལ་ལེགས་པར་བྱེད་པ་ཡི། །བྱང་ཆུབ་སེམས་དཔའ་སྨོས་ཅི་དགོས། །\nའགྲོ་བ་ཉུང་ཟད་ནར་མའི་ཟས་སྦྱོར་བ། །སྐད་ཅིག་ཟས་ཙམ་སྦྱིན་པར་བྱེད་པ་དང་། །བརྙས་བཅས་ཉིན་ཕྱེད་འགྲངས་པར་བྱེད་པ་ཡང་། །དགེ་བ་བྱེད་པ་ཡིན་ཞེས་སྐྱེ་བོས་བཀུར། །\nསེམས་ཅན་གྲངས་མཐའ་ཡས་ལ་དུས་རིང་དུ། །བདེ་བར་གཤེགས་ཀྱི་བདེ་བ་བླ་ན་མེད། །ཡིད་ལ་བསམ་པ་མཐའ་དག་རྫོགས་བྱེད་པ། །རྟག་ཏུ་སྦྱིན་པ་ལྟ་ཞིག་སྨོས་ཅི་དགོས། །\n\nགང་ཞིག་དེ་འདྲའི་རྒྱལ་སྲས་སྦྱིན་བདག་ལ། །གལ་ཏེ་ངན་སེམས་སྐྱེད་པར་བྱེད་ན་དེ། །ངན་སེམས་བསྐྱེད་པའི་གྲངས་བཞིན་བསྐལ་པར་ནི། །དམྱལ་བར་གནས་པར་འགྱུར་ཞེས་ཐུབ་པས་གསུངས། །\nའོན་ཏེ་གང་ཞིག་ཡིད་རབ་དང་བྱེད་ན། །དེ་ཡི་འབྲས་བུ་དེ་བས་ལྷག་པར་འཕེལ། །\n\nརྒྱལ་སྲས་རྣམས་ལ་དོ་གལ་ཆེན་པོས་ཀྱང་། །སྡིག་པ་མི་འབྱུང་དགེ་བ་ངང་གིས་འཕེལ། །\nགང་ལ་སེམས་ཀྱི་དམ་པ་རིན་ཆེན་དེ། །སྐྱེས་པ་དེ་ཡི་སྐུ་ལ་ཕྱག་འཚལ་ཞིང་། །གང་ལ་གནོད་པ་བྱས་ཀྱང་བདེ་འབྲེལ་བ། །བདེ་བའི་འབྱུང་གནས་དེ་ལ་སྐྱབས་སུ་མཆི།",
        "children": [
          {
            "level": "subsection",
            "number": "1.4.1",
            "title": "Worthiness of Praise",
            "verses_span": "30-32",
            "verse_text_excerpt": "ཕན་བཏགས་ལན་ལྡོན་གང་ཡིན་པ། །དེ་ཡང་རེ་ཞིག་བསྔགས་འོས་ན། །མ་བཅོལ་ལེགས་པར་བྱེད་པ་ཡི། །བྱང་ཆུབ་སེམས་དཔའ་སྨོས་ཅི་དགོས། །\nའགྲོ་བ་ཉུང་ཟད་ནར་མའི་ཟས་སྦྱོར་བ། །སྐད་ཅིག་ཟས་ཙམ་སྦྱིན་པར་བྱེད་པ་དང་། །བརྙས་བཅས་ཉིན་ཕྱེད་འགྲངས་པར་བྱེད་པ་ཡང་། །དགེ་བ་བྱེད་པ་ཡིན་ཞེས་སྐྱེ་བོས་བཀུར། །\nསེམས་ཅན་གྲངས་མཐའ་ཡས་ལ་དུས་རིང་དུ། །བདེ་བར་གཤེགས་ཀྱི་བདེ་བ་བླ་ན་མེད། །ཡིད་ལ་བསམ་པ་མཐའ་དག་རྫོགས་བྱེད་པ། །རྟག་ཏུ་སྦྱིན་པ་ལྟ་ཞིག་སྨོས་ཅི་དགོས། །",
            "children": []
          },
          {
            "level": "subsection",
            "number": "1.4.2",
            "title": "Consequences of Actions towards Bodhisattvas",
            "verses_span": "33-34",
            "verse_text_excerpt": "གང་ཞིག་དེ་འདྲའི་རྒྱལ་སྲས་སྦྱིན་བདག་ལ། །གལ་ཏེ་ངན་སེམས་སྐྱེད་པར་བྱེད་ན་དེ། །ངན་སེམས་བསྐྱེད་པའི་གྲངས་བཞིན་བསྐལ་པར་ནི། །དམྱལ་བར་གནས་པར་འགྱུར་ཞེས་ཐུབ་པས་གསུངས། །\nའོན་ཏེ་གང་ཞིག་ཡིད་རབ་དང་བྱེད་ན། །དེ་ཡི་འབྲས་བུ་དེ་བས་ལྷག་པར་འཕེལ། །",
            "children": []
          },
          {
            "level": "subsection",
            "number": "1.4.3",
            "title": "Bodhisattva's Resilience and Refuge",
            "verses_span": "35-36",
            "verse_text_excerpt": "རྒྱལ་སྲས་རྣམས་ལ་དོ་གལ་ཆེན་པོས་ཀྱང་། །སྡིག་པ་མི་འབྱུང་དགེ་བ་ངང་གིས་འཕེལ། །\nགང་ལ་སེམས་ཀྱི་དམ་པ་རིན་ཆེན་དེ། །སྐྱེས་པ་དེ་ཡི་སྐུ་ལ་ཕྱག་འཚལ་ཞིང་། །གང་ལ་གནོད་པ་བྱས་ཀྱང་བདེ་འབྲེལ་བ། །བདེ་བའི་འབྱུང་གནས་དེ་ལ་སྐྱབས་སུ་མཆི།",
            "children": []
          }
        ]
      }
    ]
  }
]